{
  "parent": "minecraft:recipes/root",
  "rewards": {
    "recipes": [
      "utilcraft:gold_wall"
    ]
  },
  "criteria": {
    "gold_brick": {
      "trigger": "minecraft:inventory_changed",
      "conditions": {
        "items": [
          {
            "items": [
              "utilcraft:gold_brick"
            ]
          }
        ]
      }
    },
    "has_the_recipe": {
      "trigger": "minecraft:recipe_unlocked",
      "conditions": {
        "recipe": "utilcraft:gold_wall"
      }
    }
  },
  "requirements": [
    [
      "gold_brick",
      "has_the_recipe"
    ]
  ]
}